MANIFEST.in
setup.py
metopes2tei/__init__.py
metopes2tei/__main__.py
metopes2tei/resources/saxon9.jar
metopes2tei/resources/ue.xsl
metopes2tei/resources/ue_archeo.xsl
metopes2tei/resources/ue_autorites.xsl
metopes2tei/resources/ue_biblio.xsl
metopes2tei/resources/ue_figures.xsl
metopes2tei/resources/ue_front.xsl
metopes2tei/resources/ue_maths.xsl
metopes2tei/resources/ue_recension.xsl
metopes2tei_CERTIC.egg-info/PKG-INFO
metopes2tei_CERTIC.egg-info/SOURCES.txt
metopes2tei_CERTIC.egg-info/dependency_links.txt
metopes2tei_CERTIC.egg-info/requires.txt
metopes2tei_CERTIC.egg-info/top_level.txt